cool_qrcode/__init__.py
cool_qrcode/core.py
cool_qrcode/exceptions.py
cool_qrcode/simple.py
cool_qrcode-0.1.3.dist-info/licenses/LICENSE
cool_qrcode-0.1.3.dist-info/METADATA
cool_qrcode-0.1.3.dist-info/WHEEL
cool_qrcode-0.1.3.dist-info/top_level.txt
cool_qrcode-0.1.3.dist-info/RECORD
