Metadata-Version: 2.4
Name: cool-qrcode
Version: 0.1.3
Summary: A Python library for generating personalized QR codes
Home-page: https://github.com/xxk59/cool-qrcode
Author: Kelvin Xu
Author-email: Kelvin Xu <xxk59@hotmail.com>
License-Expression: MIT
Project-URL: Homepage, https://github.com/xxk59/cool-qrcode
Project-URL: Repository, https://github.com/xxk59/cool-qrcode
Project-URL: Issues, https://github.com/xxk59/cool-qrcode/issues
Keywords: qrcode,qr,barcode,generator,personalized
Classifier: Development Status :: 3 - Alpha
Classifier: Intended Audience :: Developers
Classifier: Programming Language :: Python :: 3
Classifier: Programming Language :: Python :: 3.8
Classifier: Programming Language :: Python :: 3.9
Classifier: Programming Language :: Python :: 3.10
Classifier: Programming Language :: Python :: 3.11
Classifier: Programming Language :: Python :: 3.12
Classifier: Topic :: Software Development :: Libraries :: Python Modules
Classifier: Topic :: Multimedia :: Graphics
Classifier: Topic :: Utilities
Requires-Python: >=3.7
License-File: LICENSE
Requires-Dist: qrcode[pil]>=7.4.2
Requires-Dist: Pillow>=8.0.0
Requires-Dist: numpy>=1.21.0
Provides-Extra: dev
Requires-Dist: pytest>=6.0; extra == "dev"
Requires-Dist: pytest-cov; extra == "dev"
Requires-Dist: black; extra == "dev"
Requires-Dist: flake8; extra == "dev"
Requires-Dist: mypy; extra == "dev"
Dynamic: author
Dynamic: home-page
Dynamic: license-file
Dynamic: requires-python
